oc_confluence_ci_type_sync/__init__.py
oc_confluence_ci_type_sync/__main__.py
oc_confluence_ci_type_sync/ci_types_sync.py
oc_confluence_ci_type_sync/templates/ci-type-groups-and-ci-types.xhtml.template
oc_confluence_ci_type_sync-1.0.2.dist-info/LICENSE
oc_confluence_ci_type_sync-1.0.2.dist-info/METADATA
oc_confluence_ci_type_sync-1.0.2.dist-info/WHEEL
oc_confluence_ci_type_sync-1.0.2.dist-info/top_level.txt
oc_confluence_ci_type_sync-1.0.2.dist-info/RECORD
